Metadata-Version: 2.1
Name: djangorest-routes
Version: 1.2.2
Summary: 🔐 Authentication routes as a service.
Home-page: https://github.com/israelabraham/djangorest-routes
Author: Abram 🐼
Author-email: israelvictory87@gmail.com
License: MIT License
Keywords: rest_routes,djangorest,authentication,rest_routes,djangorest_routes,auth as a service,ar as a service
Platform: UNKNOWN
Classifier: Development Status :: 5 - Production/Stable
Classifier: Environment :: Web Environment
Classifier: Framework :: Django
Classifier: Framework :: Django :: 2.2
Classifier: Framework :: Django :: 3.0
Classifier: Framework :: Django :: 3.1
Classifier: Framework :: Django :: 3.2
Classifier: Framework :: Django :: 4.0
Classifier: Intended Audience :: Developers
Classifier: License :: OSI Approved :: MIT License
Classifier: Operating System :: OS Independent
Classifier: Programming Language :: Python
Classifier: Programming Language :: Python :: 3
Classifier: Programming Language :: Python :: 3 :: Only
Classifier: Programming Language :: Python :: 3.6
Classifier: Programming Language :: Python :: 3.7
Classifier: Programming Language :: Python :: 3.8
Classifier: Programming Language :: Python :: 3.9
Classifier: Programming Language :: Python :: 3.10
Classifier: Topic :: Internet :: WWW/HTTP
Classifier: Topic :: Internet :: WWW/HTTP :: Dynamic Content
Requires-Python: >=3.6
License-File: LICENSE.txt
Requires-Dist: django (>=2.2)
Requires-Dist: djangorestframework
Requires-Dist: djangorestframework-simplejwt
Requires-Dist: rest-api-payload
Requires-Dist: django-cors-headers
Requires-Dist: django-hashid-field
